cache_by_key/__init__.py
cache_by_key/cache_utils.py
cache_by_key/constants/__init__.py
cache_by_key/constants/cache_constants.py
cache_by_key/data_structure/__init__.py
cache_by_key/data_structure/cache_class.py
cache_by_key/data_structure/deque_cache_dict.py
cache_by_key-0.0.2.dist-info/LICENSE
cache_by_key-0.0.2.dist-info/METADATA
cache_by_key-0.0.2.dist-info/WHEEL
cache_by_key-0.0.2.dist-info/top_level.txt
cache_by_key-0.0.2.dist-info/RECORD
