Metadata-Version: 2.1
Name: cache-by-key
Version: 0.0.2
Summary: cache-by-key is a lru based cache that allows you to cache by specific keyword argument from a decorated function.
Home-page: https://github.com/Rashik-raj/cache-by-key
Author: Rashikraj Shrestha
Author-email: rashik123.rs@gmail.com
Project-URL: Bug Tracker, https://github.com/Rashik-raj/cache-by-key/issues
Classifier: Programming Language :: Python :: 3
Classifier: License :: OSI Approved :: MIT License
Classifier: Operating System :: OS Independent
Requires-Python: >=3.8
License-File: LICENSE
